pyzsync-1.4.20.dist-info/METADATA
pyzsync-1.4.20.dist-info/WHEEL
pyzsync-1.4.20.dist-info/licenses/LICENSE
pyzsync/__init__.py
pyzsync/__main__.py
pyzsync/py.typed
pyzsync/pyzsync.cpython-313-darwin.so
pyzsync/pyzsync.pyi
pyzsync-1.4.20.dist-info/RECORD
