Metadata-Version: 2.4
Name: pyzsync
Version: 1.4.20
License-File: LICENSE
Summary: A Python module written in Rust that implements the zsync algorithm
Author-email: uib GmbH <info@uib.de>
Maintainer-email: uib GmbH <info@uib.de>
License-Expression: AGPL-3.0-only
Requires-Python: >=3.9
